MANIFEST.in
README.md
requirements.txt
setup.py
testtfchain.egg-info/PKG-INFO
testtfchain.egg-info/SOURCES.txt
testtfchain.egg-info/dependency_links.txt
testtfchain.egg-info/requires.txt
testtfchain.egg-info/top_level.txt
tfchain/TFChainClient.py
tfchain/TFChainExplorerClient.py
tfchain/TFChainWallet.py
tfchain/__init__.py
tfchain/errors.py
tfchain/crypto/__init__.py
tfchain/crypto/merkletree.py
tfchain/encoders/__init__.py
tfchain/encoders/exceptions.py
tfchain/encoders/rivine.py
tfchain/encoders/sia.py
tfchain/internal/HttpClient.py
tfchain/internal/__init__.py
tfchain/internal/jsutils.py
tfchain/types/AtomicSwap.py
tfchain/types/BaseDataType.py
tfchain/types/ConditionTypes.py
tfchain/types/CryptoTypes.py
tfchain/types/ERC20.py
tfchain/types/FulfillmentTypes.py
tfchain/types/IO.py
tfchain/types/PrimitiveTypes.py
tfchain/types/ThreeBot.py
tfchain/types/__init__.py
tfchain/types/transactions/Base.py
tfchain/types/transactions/ERC20.py
tfchain/types/transactions/Minting.py
tfchain/types/transactions/Standard.py
tfchain/types/transactions/ThreeBot.py
tfchain/types/transactions/Transactions.py
tfchain/types/transactions/__init__.py