Metadata-Version: 1.1
Name: testtfchain
Version: 0.1.1
Summary: pythonic tfchain client
Home-page: https://github.com/glendc/tfchain-py
Author: Glen De Cauwsemaecker
Author-email: glen@threefold.tech
License: MIT License
Platform: UNKNOWN
Classifier: Development Status :: 4 - Beta
Classifier: Environment :: Console
Classifier: Intended Audience :: Developers
Classifier: License :: OSI Approved :: MIT License
Classifier: Operating System :: OS Independent
Classifier: Programming Language :: Python
